zc.py
zc-0.1.1.dist-info/WHEEL
zc-0.1.1.dist-info/METADATA
zc-0.1.1.dist-info/RECORD
